fitland/__init__.py
fitland/auth.py
fitland/lib.py
fitland/n_types.py
fitland/version.py
fitland/models/__init__.py
fitland/models/area.py
fitland/models/athlete.py
fitland/models/athlete_fitcard.py
fitland/models/athlete_listeners.py
fitland/models/athlete_result.py
fitland/models/athlete_score.py
fitland/models/competition.py
fitland/models/competition_fitcard.py
fitland/models/currency.py
fitland/models/division.py
fitland/models/heat.py
fitland/models/judge.py
fitland/models/notification.py
fitland/models/permissions.py
fitland/models/permissions_action.py
fitland/models/phase.py
fitland/models/role.py
fitland/models/scores.py
fitland/models/settings.py
fitland/models/staff.py
fitland/models/team.py
fitland/models/team_fitcard.py
fitland/models/team_listeners.py
fitland/models/team_result.py
fitland/models/team_score.py
fitland/models/user.py
fitland/models/workout.py
fitland-0.2.2.dist-info/METADATA
fitland-0.2.2.dist-info/WHEEL
fitland-0.2.2.dist-info/top_level.txt
fitland-0.2.2.dist-info/RECORD
