Metadata-Version: 2.1
Name: fitland
Version: 0.2.2
Summary: Common Fitland Development Module
Home-page: https://github.com/byndmx/pyfitland
Author: Erick Salas
Author-email: erick.salas@ermiry.com
License: UNKNOWN
Project-URL: Bug Tracker, https://github.com/byndmx/pyfitland/issues
Platform: UNKNOWN
Classifier: Programming Language :: Python :: 3
Classifier: License :: OSI Approved :: MIT License
Classifier: Operating System :: OS Independent
Requires-Python: >=3.6
